[{"id":"1","situation":"한 남자가 바닷가 고급 레스토랑에서 바다거북 수프를 주문했어요. 한 수저 먹고 주방장에게 \"이거 진짜 바다거북 수프예요?\"라고 묻고, 계산한 뒤 집에 가서 자살했어요. 왜일까요?","clues":["남자는 과거에 조난을 겪었어요."],"answer":"조난 후 동료들은 인육으로 수프를 끓이며 바다거북 수프라고 속였고, 남자만 그 사실을 몰랐어요. 레스토랑에서 진짜 바다거북 수프 맛을 알자 그때 먹은 것이 인육이었음을 깨달아 자살한 거예요."},{"id":"2","situation":"한 남자가 바에 들어가 \"물 한 잔 주세요\"라고 했어요. 바텐더는 총을 꺼내 겨눴고, 남자는 \"감사합니다\"라고 하고 나갔어요. 왜일까요?","clues":["남자는 바텐더를 해치려 한 게 아니에요.","총은 남자를 깜짝 놀라게 하려는 용도였어요.","남자가 겪고 있던 신체 반응이 갑자기 멈췄어요."],"answer":"남자는 심한 딸꾹질을 하고 있었어요. 총을 겨누어 놀라게 하자 딸꾹질이 멈췄고, 그래서 감사하다며 물 없이 나간 거예요."},{"id":"3","situation":"한 남자는 30층 아파트에 사는데, 퇴근하면 엘리베이터로 10층까지만 타고 계단으로 올라가요. 비 오는 날만 30층까지 타요. 왜일까요?","clues":["운동하려고 계단을 걷는 게 아니에요.","엘리베이터 버튼을 누를 수 있는 높이와 관련이 있어요.","비 오는 날만 추가로 손에 쥐는 물건이 있어요."],"answer":"키가 작아 30층 버튼에 손이 닿지 않아요. 10층까지만 누를 수 있어 평소엔 10층에서 내려 걸어 올라가고, 비 오는 날 우산 끝으로 30층 버튼을 누를 수 있었던 거예요."},{"id":"4","situation":"들판 한가운데 남자가 죽어 있었고, 주변에는 열리지 않은 패키지 하나만 있었어요. 어떻게 죽었을까요?","clues":["패키지는 남자의 죽음과 직접 연결돼요.","남자는 높은 곳에서 떨어졌어요.","패키지 안에 있어야 할 것이 제대로 작동하지 않았어요."],"answer":"비행기에서 낙하산을 메고 뛰어내렸는데 낙하산이 펼쳐지지 않았어요. 예비 낙하산이 든 패키지를 열기도 전에 지면에 추락해 죽은 거예요."},{"id":"5","situation":"천장에 밧줄이 달린 빈 방에서 남자가 목을 매어 죽어 있었고, 바닥엔 물웅덩이만 있었어요. 발판은 없었어요. 어떻게 자살했을까요?","clues":["의자나 발판 같은 물건은 없었어요.","바닥 물은 무언가가 녹아 생긴 거예요.","얼음을 이용했어요."],"answer":"얼음 블록 위에 올라가 밧줄에 목을 맸어요. 시간이 지나 얼음이 녹아 물웅덩이가 되고 발판을 잃어 목이 조여진 거예요."},{"id":"6","situation":"무인도에서 남편은 일시적으로 실명했어요. 아내가 구해온 \"갈매기 고기\"를 먹고 회복해 구조됐는데, 나중에 갈매기 고깃집에서 한 입 먹고 절망해 바다로 뛰어들었어요. 왜일까요?","clues":["무인도에서 먹은 고기는 갈매기가 아니었어요.","아내의 몸과 관련된 희생이 있었어요.","진짜 갈매기 고기 맛이 그때와 달랐어요."],"answer":"아내는 자신의 허벅지 살을 구워 갈매기 고기라고 속였어요. 실명한 남편은 모르고 먹었고, 시력을 되찾은 뒤 진짜 갈매기 맛을 알자 그때 먹은 것이 아내의 살이었음을 깨달은 거예요."},{"id":"7","situation":"한 여자가 문을 열더니 비명을 지르고 곧 죽었어요. 총소리는 없었어요. 무슨 일이었을까요?","clues":["문은 비행기 안에 있었어요.","비행기는 비행 중이었어요.","문을 연 행위가 직접적인 원인이에요."],"answer":"비행 중 비상문을 열어 기압 차로 밖으로 빨려 나가 사망했어요. 그래서 총소리 같은 소리는 없었던 거예요."},{"id":"8","situation":"한 남자가 스키장에서 다이아몬드를 밟았더니 다리가 부러졌어요. 어떻게 된 걸까요?","clues":["다이아몬드는 보석이 아니에요.","스키장에서 쓰는 난이도 표현이에요.","그가 탄 코스의 이름·등급과 관련이 있어요."],"answer":"\"블랙 다이아몬드\"는 고난도 스키 슬로프를 뜻해요. 그 코스에서 넘어져 다리가 부러진 거예요."},{"id":"9","situation":"스킨스쿠버 차림의 남자가 새까맣게 탄 나무에 매달려 죽어 있었어요. 숲에 화재가 났고 호수가 가까웠어요. 왜 그렇게 됐을까요?","clues":["남자는 호수에서 잠수 중이었어요.","산불 진압을 위해 헬리콥터가 물을 퍼 올렸어요.","그 과정에서 남자가 함께 끌려 올라갔어요."],"answer":"소방 헬기가 호수에서 물을 퍼 올릴 때 스킨스쿠버 하던 남자까지 빨려 들어갔어요. 불 위로 물을 뿌릴 때 나무에 걸려 그렇게 된 거예요."},{"id":"10","situation":"남자가 차를 끌고 호텔에 도착하자마자 자신이 파산했다는 걸 깨달았어요. 무슨 일이었을까요?","clues":["진짜 자동차가 아니에요.","호텔도 실제 건물이 아니에요."],"answer":"모노폴리 같은 게임에서 차 모양 말을 호텔 칸까지 밀었는데, 통행료를 낼 돈이 없어 파산한 거예요."},{"id":"11","situation":"30층 아파트에 사는 남자가 창문에서 뛰어내렸는데 부상 없이 살았어요. 어떻게 가능할까요?","clues":["그는 30층에 산다고 말은 했어요.","뛰어내린 창문의 층수가 달랐어요.","낙하 높이가 매우 낮았어요."],"answer":"뛰어내린 창문은 1층이었어요. 건물은 30층이지만 1층에서 뛰어내렸기 때문에 크게 다치지 않은 거예요."},{"id":"12","situation":"한 여자가 열 명의 남자와 결혼했는데 이혼도 없고 남편이 죽은 것도 아니에요. 어떻게 가능할까요?","clues":["법적으로 한 번에 한 사람과만 혼인한 상태예요.","그녀의 직업과 관련이 있어요.","결혼식은 연기였어요."],"answer":"배우로 드라마·영화에서 결혼 장면을 열 번 연기한 거예요. 실제 혼인 관계는 아니에요."},{"id":"13","situation":"남자가 시속 200km로 질주했는데 경찰이 단속하지 않았어요. 왜일까요?","clues":["도로 교통법 위반이 아니에요.","그가 달린 장소가 특별해요.","공식 경기·트랙과 관련이 있어요."],"answer":"F1 등 레이스 트랙에서 경기 중이었어요. 그 속도는 규정 안에서의 주행이라 일반 단속 대상이 아니었던 거예요."},{"id":"14","situation":"아이가 \"극장에서 남자가 살해당하는 걸 봤다\"고 했는데 아무도 신고하지 않았어요. 왜일까요?","clues":["실제 살인 사건이 아니에요."],"answer":"링컨 대통령이 극장에서 암살당한 역사를 발표한 거예요. 현재 범죄가 아니라서 신고가 없었던 거예요."},{"id":"15","situation":"여자가 아침엔 런던행 비행기, 점심은 뉴욕, 저녁 8시 라스베이거스 쇼를 같은 날 예약했어요. 모두 갈 수 있을까요?","clues":["그녀 본인이 세 도시를 몸으로 이동하는 건 아니에요.","여행 업무와 관련이 있어요.","예약은 서로 다른 사람을 위한 것이에요."],"answer":"여행사 직원이 세 명의 고객을 위해 각각 예약한 거예요. 그녀가 하루에 세 곳을 도는 게 아니에요."},{"id":"16","situation":"사막 한가운데 섬에 갇혔는데 배도 없이 수영하지 않고 탈출했어요. 어떻게 했을까요?","clues":["물가와 연결되는 길이 시간에 따라 생겨요.","조수·썰물과 관련이 있어요.","물이 빠지면 걸어 나갈 수 있어요."],"answer":"썰물 때 모래톱이 드러나 육지나 다른 섬과 이어졌어요. 그 길을 걸어 탈출한 거예요."},{"id":"17","situation":"여자가 카운터 너머 남자에게 책을 건넸어요. \"4달러입니다\"라고 했고, 여자는 돈을 내고 책 없이 나갔어요. 남자도 막지 않았어요. 왜일까요?","clues":["책을 새로 사러 온 게 아니에요.","4달러는 상품 가격이 아니에요.","도서관이에요."],"answer":"연체된 책을 반납하며 연체료 4달러를 낸 거예요. 반납만 했으니 책을 가져가지 않는 게 당연해요."},{"id":"18","situation":"부부가 주차된 차 안에 있었는데, 낯선 사람이 탔는데도 놀라지 않았어요. 왜일까요?","clues":["탄 사람은 갓난아기였어요.","차 안에서 출산이 있었어요.","처음 보는 얼굴이 맞지만 부부에게는 기쁜 일이에요."],"answer":"차 안에서 아기가 태어났어요. 낯선 사람은 막 태어난 아기였던 거예요."},{"id":"19","situation":"남자는 매일 같은 여자의 조언을 믿고 따랐는데, 그 여자를 만날 생각은 없었어요. 왜일까요?","clues":["그 여자는 실제 사람이 아니에요.","운전 중에 듣는 목소리예요."],"answer":"내비게이션의 여성 음성 안내예요. 목소리는 매일 따르지만 사람으로 만나지는 않죠."},{"id":"20","situation":"문 너머 방에서 밤새 손이 옆에 고정된 채 잡혀 있던 존재가 가끔 울었어요. 카메라로 지켜봐도 아무도 신고하지 않았고, 아침엔 행복해했어요. 왜일까요?","clues":["그 존재는 아기였어요.","손 고정은 포대기예요.","카메라는 베이비 모니터예요."],"answer":"포대기에 싼 아기가 밤에 울다 잠들었고, 부모는 모니터로만 봤어요. 아침에 잘 잔 아기는 행복해 보인 거예요."},{"id":"21","situation":"세 방 중 하나로 들어가야 해요. 첫째 방은 총 든 총격대, 둘째는 불, 셋째는 6개월 굶은 호랑이들. 어디가 가장 안전할까요?","clues":["호랑이는 오랫동안 먹이를 받지 못했어요.","살아 있는 호랑이와 죽은 호랑이는 다르게 취급해야 해요.","불과 총격대는 여전히 위험해요."],"answer":"6개월 동안 먹이가 없었다면 호랑이는 이미 죽었을 가능성이 커요. 세 번째 방이 상대적으로 가장 안전한 거예요."},{"id":"22","situation":"3살 릴리가 사라졌는데 FBI와 경찰이 수사를 도와주지 않았어요. 왜일까요?","clues":["릴리는 사람이 아니에요.","가족이 애타게 찾는 대상의 종류가 달라요.","실종 전단은 일반적인 반려동물 찾기예요."],"answer":"릴리는 개 이름이에요. 사람 실종이 아니라서 경찰이나 FBI가 나서지 않은 거예요."},{"id":"23","situation":"남자가 총을 쏜 뒤 곧 실수를 깨달았고, 잠시 뒤 살인자도 죽었어요. 총소리만이 원인은 아니에요. 무슨 일이었을까요?","clues":["눈 덮인 산이나 절벽 근처였어요.","총소리·진동이 주변 환경을 무너뜨렸어요.","눈사태와 관련이 있어요."],"answer":"총을 쏘자 눈사태가 났고, 살인자까지 눈사태에 휩쓸여 죽은 거예요."},{"id":"24","situation":"여자가 매일 살인을 저지르는데 신고가 없고, 가족에게 전리품을 보여줘도 문제가 안 돼요. 왜일까요?","clues":["그녀는 고양이예요.","피해자는 작은 동물이에요.","집사에게 쥐를 가져다주는 일이에요."],"answer":"고양이가 쥐나 새를 잡아 오는 거예요. 사람 살인이 아니라서 신고되지 않는 거예요."},{"id":"25","situation":"폭발물이 있다며 대피했는데 건물이 무너졌어도 수사·체포가 없었어요. 왜일까요?","clues":["폭발은 허가된 작업이었어요.","건물 철거와 관련이 있어요.","범죄가 아닌 공사 절차예요."],"answer":"계획된 건물 폭파 철거였어요. 안전하게 대피시킨 뒄 합법적으로 무너뜨린 거라 수사 대상이 아니에요."},{"id":"26","situation":"잭과 질이 거실 바닥에서 깨진 유리와 물에 둘러싸여 죽어 있었어요. 흉기는 없었어요. 무슨 일이었을까요?","clues":["잭과 질은 사람 이름이 아니에요.","유리와 물은 작은 수조와 관련이 있어요.","반려용 생물이에요."],"answer":"잭과 질은 금붕어 이름이에요. 어항이 깨지고 물이 쏟아져 물고기가 죽은 거예요."},{"id":"27","situation":"50년 넘은 차가 불타며 큰 사고를 냈는데 구급·군이 와도 부상자가 없었어요. 어떻게 가능할까요?","clues":["실제 도로 사고가 아니에요."],"answer":"레이싱 게임 등에서 차가 폭발·추락한 장면이었어요. 현실 부상자는 없는 거예요."},{"id":"28","situation":"여자가 남자의 반지를 잡아당겼어요. 곧 둘 다 죽었어요. 왜일까요?","clues":["반지는 액세서리가 아니에요.","폭발물의 부품과 비슷한 모양이에요."],"answer":"수류탄의 안전핀(반지 모양)을 잡아당긴 거예요. 폭발로 둘 다 사망한 거예요."},{"id":"29","situation":"국제 팀 동료가 피에 둘러싸인 채 살해당했는데 발자국은 없고, 여러 나라가 알아도 당장 체포가 어려웠어요. 왜일까요?","clues":["현장은 지구 밖이에요.","무중력 환경이에요.","우주 정거장과 관련이 있어요."],"answer":"국제우주정거장에서의 사건이에요. 무중력이라 피가 떠다니며 발자국이 없고, 범인 처리는 귀환 시점 등의 문제로 복잡한 거예요."},{"id":"30","situation":"남자가 잔인한 살인을 계획·실행했다고 자세히 말했는데 체포되지 않았어요. 왜일까요?","clues":["그는 작가예요.","살인은 허구의 줄거리예요.","방송·인터뷰는 작품 홍보였어요."],"answer":"소설이나 시나리오 내용을 설명한 거예요. 실제 범죄가 아니라서 체포되지 않은 거예요."},{"id":"31","situation":"남자가 시속 65km 구간에서 60km로 가는 차 세 대를 지나쳤는데 역주행 딱지를 뗐어요. 왜일까요?","clues":["숫자만 보면 제한 속도를 넘지 않았어요.","진행 방향이 잘못됐어요.","반대 차선 차량들을 마주친 거예요."],"answer":"고속도로 역주행 중이었어요. 마주 오는 차가 60km로 달리는 것처럼 보였을 뿐, 본인의 진행은 위반이었던 거예요."},{"id":"32","situation":"두 남자가 같은 음료를 마셨는데 한 명만 죽었어요. 왜일까요?","clues":["음료 자체는 같은 레시피예요.","한쪽만 특정 성분에 치명적이었어요.","알레르기와 관련이 있어요."],"answer":"한 남자만 땅콩 등 특정 성분에 심한 알레르기가 있었어요. 같은 잔을 마셔도 반응이 다른 거예요."},{"id":"33","situation":"여자가 주인이 있는 집에 들어가 아무 말 없이 물건을 가져 나갔어요. 왜 괜찮았을까요?","clues":["그녀는 의뢰를 받고 온 사람이에요.","가져간 것은 버릴 것들이에요.","청소·수거 업무와 관련이 있어요."],"answer":"청소부가 쓰레기를 수거해 나간 거예요. 주인이 맡긴 일이라 제지하지 않은 거예요."},{"id":"34","situation":"조는 1955년에 태어나 1980년에 75세로 죽었어요. 어떻게 가능할까요?","clues":["1955와 1980이 연도가 아닐 수 있어요.","장소 번호·호실 번호일 수 있어요.","병원 건물과 관련이 있어요."],"answer":"1955호에서 태어나 1980호 병실에서 75세의 나이로 사망한 거예요. 숫자는 연도가 아니라 호실 번호였던 거예요."},{"id":"35","situation":"어두운 방에 성냥, 기름등, 벽난로, 촛불이 있어요. 무엇을 가장 먼저 켜야 할까요?","clues":["나머지를 켜려면 먼저 불을 일으킬 수단이 필요해요.","성냥은 한 번만 쓸 수 있는 출발점이에요.","다른 것들은 성냥 이후에 점화할 수 있어요."],"answer":"성냥을 먼저 켜야 해요. 성냥으로 불을 붙여야 기름등·벽난로·촛불에 불을 옮길 수 있어요."},{"id":"36","situation":"여자가 2주마다 종이 60장에 단 두 단어만 써요. 왜일까요?","clues":["두 단어는 서명·이름과 관련이 있어요.","직원 수와 장 수가 맞아요.","경영자의 정기 업무일 수 있어요."],"answer":"직원 60명에게 급여명세서에 서명하는 사장이에요. 2주마다 60장에 자기 이름(두 단어 분량)을 쓰는 거예요."},{"id":"37","situation":"남자가 숲에서 여러 번 총에 맞았는데 큰 부상 없이 살았어요. 어떻게 된 걸까요?","clues":["실탄이 아니에요.","페인트가 묻는 장비예요."],"answer":"페인트볼 게임이었어요. 맞아도 실제 총상이 아니에요."},{"id":"38","situation":"문 뒤 방에서 여러 목소리가 났는데, 안에는 한 사람만 조용히 앉아 있었어요. 왜일까요?","clues":["목소리는 그 사람 입에서 나온 게 아니에요.","전자 기기에서 재생됐어요.","혼자 시청 중이어도 여러 화자가 들릴 수 있어요."],"answer":"TV나 영상을 보고 있었어요. 화면 속 여러 사람의 대화 소리가 들린 거예요."},{"id":"39","situation":"세 사람이 방에 들어갔는데 두 사람만 걸어 나왔어요. 방은 비었어요. 세 번째는?","clues":["세 번째는 걸음마를 하지 않는 나이예요.","기어서 이동했어요.","아기와 관련이 있어요."],"answer":"세 번째는 아기였어요. 기어서 나왔기 때문에 걸어 나온 두 사람과 표현이 달라진 거예요."},{"id":"40","situation":"아이가 같은 날 아침 7시에 아침·점심·저녁을 모두 먹었어요. 어떻게 가능할까요?","clues":["비행기나 긴 이동이 있었어요."],"answer":"시차를 넘나드는 비행으로, 각 지역에서 현지 시각 7시에 아침·점심·저녁을 먹은 거예요."},{"id":"41","situation":"비 오는 날 우산 없이 건물에 들어왔는데 머리카락이 전혀 젖지 않았어요. 왜일까요?","clues":["비를 안 맞은 건 아니에요.","젖을 머리카락이 원래 없어요.","두발의 상태가 특이해요."],"answer":"대머리라서 머리카락이 없었어요. \"머리카락이 젖지 않았다\"는 말이 그대로 맞는 거예요."},{"id":"42","situation":"여자가 스테이크를 주문해 한 입 먹고 조용히 자리를 떴어요. 불만은 없었어요. 왜일까요?","clues":["맛을 평가하는 직업이에요.","한 입이면 업무 목적을 달성해요.","다음 일정이 있었어요."],"answer":"음식 평론가 등으로 맛만 확인하고 이동한 거예요."},{"id":"43","situation":"어두운 방의 촛불이 아무도 끄지 않았는데 꺼졌어요. 왜일까요?","clues":["바람으로 꺼진 게 아니에요.","연료가 다 소모됐어요.","시간이 지나면 자연스럼게 소멸해요."],"answer":"촛불이 다 타서 스스로 꺼진 거예요."},{"id":"44","situation":"두 아들이 같은 해·달·시각에 태어났는데 쌍둥이가 아니래요. 왜일까요?","clues":["형제 수가 둘만이 아닐 수 있어요.","삼둥이 이상이에요.","같은 시각 태어난 형제가 셋 이상이에요."],"answer":"삼둥이 이상이라 \"두 아들\"만 골라 말하면 쌍둥이(둘만 동시 출생)로 부르기 애매한 거예요."},{"id":"45","situation":"남자가 상어가 있는 피 물 속에 둘러싸였는데 전혀 걱정하지 않았어요. 왜일까요?","clues":["그는 철망·케이지 안에 있어요.","상어는 체험·관람 시설 쪽이에요.","피는 끌어들이기 위해 넣은 거예요."],"answer":"상어 다이빙용 케이지 안에서 안전하게 관찰 중이었어요."},{"id":"46","situation":"잔디밭에 석탄 여섯 개, 당근, 스카프가 있었어요. 아무도 두지 않았어요. 무슨 일이었을까요?","clues":["겨울에 만들었다가 사라진 것이 있어요.","눈으로 만든 존재의 잔재예요."],"answer":"눈사람이 녹아 눈·단추(석탄), 코(당근), 스카프만 남은 거예요."},{"id":"47","situation":"남자가 바다에서 랍스터를 잡다가 상어를 봤는데 걱정하지 않았어요. 왜일까요?","clues":["그날은 실제로 바다에 나가지 않았어요.","상어는 유리 너머예요.","수족관·전시와 관련이 있어요."],"answer":"수족관을 구경하거나 체험하는 중이었어요. 상어는 탱크 안에 있었던 거예요."},{"id":"48","situation":"달걀 12개 곽에서 12명이 각각 하나씩 가져갔는데 곽 안에 달걀이 하나 남았어요. 왜일까요?","clues":["마지막 사람의 가져간 방식이 달라요.","달걀만 들고 간 게 아닐 수 있어요.","곽째로 가져갔어요."],"answer":"마지막 사람이 달걀 하나를 곽에 넣은 채 통째로 가져갔어요. 그래서 \"곽 안에 달걀이 하나\"가 남은 것처럼 말해지는 거예요."},{"id":"49","situation":"남자가 파티 후 집 문 앞인데 들어갈 수 없었어요. 자기 집이 맞는데도요. 왜일까요?","clues":["열쇠가 없었어요.","친구들이 안전을 위해 가져갔어요.","술과 관련이 있어요."],"answer":"과음해서 친구가 열쇠를 빼앗고 택시로 보냈어요. 열쇠 없이 문을 열 수 없었던 거예요."},{"id":"50","situation":"아버지가 망치로 뭘 고쳤더니 아버지는 게임을 할 수 있는데 아들은 못 해요. 뭘 했을까요?","clues":["게임기의 높이가 바뀌었어요.","아버지와 아들의 키 차이가 중요해요.","선반이나 걸이를 만들었어요."],"answer":"아들 손이 닿지 않는 높이에 선반을 달아 게임기를 올려둔 거예요. 아버지는 닿고 아들은 못 닿는 거예요."},{"id":"51","situation":"전화부스 안 남자가 죽었고 안은 물로 가득했어요. 겨울 호수 위였어요.","clues":["부스가 얼음 위에 있었어요."],"answer":"얼음 낚시 구멍 등 위에 놓인 부스가 얼음과 함께 가라앉아 익사한 거예요."},{"id":"52","situation":"소문으로, 남자가 성냥을 켜고 창밖을 본 뒤 죽었어요. 잠수함 안이었어요.","clues":["실수 신호와 관련 있어요.","다른 잠수함이 있었어요."],"answer":"잠수함 간 신호를 성냥으로 잘못 보내 공격받았거나 충돌한 거예요."},{"id":"53","situation":"어느 마을에서 남자는 매일 지하철로 출근하는데 퇴근만 계단으로 올라가요. 같은 역이에요.","clues":["출근은 내려가는 방향이에요.","직장이 지하에 있어요.","퇴근은 위로 나와야 해요."],"answer":"지하 깊은 곳(광산·연구소 등)에서 일하고 올라올 때만 계단을 쓰는 거예요."},{"id":"54","situation":"뉴스 한 줄. 여자는 매일 엘리베이터로 내려가기만 하고 올라탄 적이 없어요. 살고 있는 건물이에요.","clues":["그녀는 키가 작아요."],"answer":"키가 작아 혼자서는 상층 버튼을 못 누르고, 내려갈 때만 1층 버튼을 누를 수 있는 거예요."},{"id":"55","situation":"친구가 들려준 남자가 총 한 발을 쐈는데 세 명이 죽었어요.","clues":["한 발에 세 명이 맞은 건 아니에요.","연쇄 사고가 났어요."],"answer":"유조차 타이어를 맞춰 폭발·연쇄 추돌로 추가 사망이 난 거예요."},{"id":"56","situation":"아이가 아빠를 보고 \"저 사람은 내 아빠가 아니에요\"라고 했는데 거짓말이 아니었어요.","clues":["아이는 거짓말하지 않았어요.","말하는 아이의 아빠는 다른 사람이에요.","가족 구성이 특이해요."],"answer":"말한 아이는 친아빠가 따로 있고, 앞에 있는 남자는 의붓아버지나 삼촌 등인 거예요."},{"id":"57","situation":"소문으로, 시체 옆에 물 한 웅덩이와 깃털이 있었어요. 어떻게 죽었을까요?","clues":["새가 직접 죽인 건 아니에요."],"answer":"살인자가 얼음으로 만든 날카로운 무기를 썼고, 녹아 물이 되고 깃털은 베개·이불 등에서 온 거예요."},{"id":"58","situation":"어느 마을에서 남자가 \"아무도 내 이름을 부르지 마\"라고 했는데 곧 죽었어요.","clues":["이름을 부른 사람이 있었어요.","그는 숨어 있었어요."],"answer":"도망 중이었는데 누군가 이름을 불러 위치가 들켜 잡히거나 공격당한 거예요."},{"id":"59","situation":"뉴스 한 줄. 한 여자가 남편 장례식에서 웃었는데 아무도 비난하지 않았어요.","clues":["그녀는 냉정한 게 아니에요.","웃음의 이유가 따로 있어요.","남편이 연기 중이었어요."],"answer":"남편이 살아 있었거나, 장례식이 연극·촬영이었거나, 기쁜 소식을 들은 거예요."},{"id":"60","situation":"친구가 들려준 남자가 물 한 방울 없이 사막을 건넜어요.","clues":["그는 걸어가지 않았어요."],"answer":"비행기나 열차 등으로 사막 위를 통과한 거예요."},{"id":"61","situation":"남자가 칼에 찔려 피 한 방울 안 나왔어요.","clues":["그는 사람이 아니에요.","인형·조각이었어요."],"answer":"인형이나 영화 소품이었어요."},{"id":"62","situation":"소문으로, 방 안에 시체와 물고기 한 마리가 있었어요. 물고기는 어떻게 들어왔을까요?","clues":["문은 잠겨 있었어요.","물고기는 살아 있지 않았어요.","통·병으로 들어왔어요."],"answer":"캔·병에 든 생선이나 표본이었어요."},{"id":"63","situation":"어느 마을에서 남자가 음악을 들으며 수영하다 익사했는데 귀는 마른 상태였어요.","clues":["수영은 실제 물이 아니에요."],"answer":"VR 수영이나 게임 속이었고 실제로 물에 들어가지 않았거나, 다른 방식의 사고였어요."},{"id":"64","situation":"뉴스 한 줄. 여자가 거울을 보고 울었어요. 거울은 정상이었어요.","clues":["그녀는 자신의 모습을 처음 본 게 아니에요.","상황이 바뀐 뒤 거울을 봤어요."],"answer":"이별·상실 후 같은 얼굴이지만 처지가 달라져 슬퍼진 거예요."},{"id":"65","situation":"친구가 들려준 남자가 책을 읽다 죽었어요. 독이 든 책은 아니었어요.","clues":["책 내용이 충격이었어요.","심장마비·과도한 스트레스와 관련 있어요.","소설 속 반전이었어요."],"answer":"충격적인 내용을 읽고 급사했거나, 책을 읽던 중 천장 등 낙하물에 맞은 거예요."},{"id":"66","situation":"두 사람이 같은 버스를 탔는데 한 명만 요금을 냈어요.","clues":["다른 한 명은 무료 대상이에요."],"answer":"한 명은 유아이거나 무료 승차 대상이거나 승무원인 거예요."},{"id":"67","situation":"소문으로, 남자가 밤에 길을 걷다 달을 보고 죽었어요.","clues":["달이 원인은 아니에요.","길을 보지 않고 하늘만 봤어요."],"answer":"하늘만 보고 걷다 교통사고를 당한 거예요."},{"id":"68","situation":"어느 마을에서 시체는 있었는데 범인의 지문은 어디에도 없었어요.","clues":["범인은 사람이 아니에요.","동물·기계·자연재해예요."],"answer":"동물 공격, 낙석, 기계 사고 등 사람 범행이 아니었어요."},{"id":"69","situation":"뉴스 한 줄. 남자가 커피를 마시고 죽었는데 커피는 정상이었어요.","clues":["다른 행동과 겹쳤어요."],"answer":"커피 자체는 무해했지만 다른 원인(기저질환, 약, 사고)이 겹친 거예요."},{"id":"70","situation":"친구가 들려준 한 여자가 매일 남의 집 편지함을 열어봐도 범죄가 아니에요.","clues":["그녀는 우편배달부예요.","직업상 권한이 있어요."],"answer":"우편집배원이 일을 하는 거예요."},{"id":"71","situation":"남자가 물속에서 숨을 쉬었어요. 마술이 아니에요.","clues":["담수가 아니에요.","액체가 물이 아닐 수 있어요.","과학 실험용 액체예요."],"answer":"산소가 녹아 있는 특수 액체나 얕은 물에서 튜브를 쓴 거예요. (또는 \"물\"이 아닌 다른 투명 액체)"},{"id":"72","situation":"소문으로, 아이가 부모 없이 병원에서 나왔어요. 납치가 아니에요.","clues":["아이는 막 태어났어요."],"answer":"갓 태어나 퇴원 준비 중인 정상 절차예요."},{"id":"73","situation":"어느 마을에서 남자가 침대에서 자다가 아침에 다른 나라에서 깼어요.","clues":["비행기 침대·기차 침대예요.","국경을 넘는 야간 이동이에요."],"answer":"국제열차나 비행기 등에서 잠든 사이 국경을 넘은 거예요."},{"id":"74","situation":"뉴스 한 줄. 여자가 꽃을 선물받고 화를 냈어요. 꽃은 시들지 않았어요.","clues":["그녀는 알레르기가 있어요.","꽃 종류가 금기예요.","장례식장에서 장미를 받은 등 문맥이 있어요."],"answer":"장례·이별 상황에서 부적절한 꽃이었거나 알레르기였어요."},{"id":"75","situation":"친구가 들려준 남자가 돈을 주고 아무것도 받지 않았는데 만족했어요.","clues":["빚을 갚았어요."],"answer":"벌금 납부나 대출 상환 등으로 \"받을 물건\"이 없는 거예요."},{"id":"76","situation":"시계는 멈췄는데 사람들은 정확한 시간을 알아요.","clues":["다른 시계가 있어요.","스마트폰이에요."],"answer":"벽시계만 고장 났고 전자기기로 시간을 보는 거예요."},{"id":"77","situation":"소문으로, 남자가 자신의 장례식에 참석했어요.","clues":["그는 살아 있어요.","연습·리허설이거나 사기 장례식이에요."],"answer":"연극 리허설, 영화 촬영, 또는 사기로 위장한 장례식이에요."},{"id":"78","situation":"어느 마을에서 여자가 이웃을 살해했다고 신고했는데 체포되지 않았어요.","clues":["이웃은 사람이 아니에요."],"answer":"벌레나 쥐 등 \"이웃\"을 은유적으로 말한 거예요."},{"id":"79","situation":"뉴스 한 줄. 남자가 하루에 두 번 생일을 맞았어요.","clues":["날짜 변경선과 관련 있어요.","비행기로 하루를 두 번 넘겼어요."],"answer":"날짜 변경선을 넘나들며 현지에서는 같은 날 두 번 생일처럼 된 거예요."},{"id":"80","situation":"친구가 들려준 문이 잠겨 있는 방에서 남자가 사라졌어요. 비밀통로는 없어요.","clues":["그는 처음부터 밖에 없었어요.","영상·사진 속 방이었어요.","녹화 화면이었어요."],"answer":"녹화된 영상 속 인물이었거나, 착시·트릭 사진이었어요."},{"id":"81","situation":"남자가 말 없이 은행에서 돈을 가져갔는데 강도가 아니에요.","clues":["그는 직원이에요."],"answer":"은행 직원이 정상 업무로 현금을 옮긴 거예요."},{"id":"82","situation":"소문으로, 아이가 학교에서 \"엄마가 죽였다\"고 했는데 선생님이 웃었어요.","clues":["보드게임·역할극이에요.","인형 놀이예요."],"answer":"인형 놀이나 게임에서의 이야기였어요."},{"id":"83","situation":"어느 마을에서 남자가 물 위를 걸었어요. 종교적 기적이 아니에요.","clues":["물이 얕아요.","다리·보트·얼음이 있어요."],"answer":"얕은 물이나 잠긴 다리, 얼어붙은 호수 위를 걸은 거예요."},{"id":"84","situation":"뉴스 한 줄. 여자가 남편에게 이혼을 요구하지 않았는데 이혼이 성립했어요.","clues":["법원 판결·실종 선고가 있었어요."],"answer":"법적 절차로 자동 이혼·실종 처리 등이 된 거예요."},{"id":"85","situation":"친구가 들려준 남자가 자기 집에서 길을 잃었어요.","clues":["집이 매우 커요.","미로 같은 구조거나 어둠이에요."],"answer":"대저택 미로, 정전, 또는 가상현경 속이었어요."},{"id":"86","situation":"시체 주머니에 돌이 들어 있었어요.","clues":["강에서 건져 올린 거예요.","시체를 가라앉히려 한 거예요."],"answer":"물에 빠진 시체를 가라앉히기 위해 주머니에 돌을 넣은 거예요."},{"id":"87","situation":"소문으로, 남자가 달리기 시합에서 이겼는데 상대는 더 빨랐어요.","clues":["목적지가 달랐어요."],"answer":"더 짧은 거리나 반대 방향 목표라 먼저 도착한 거예요."},{"id":"88","situation":"어느 마을에서 여자가 매일 밤 소리 없이 우편함을 비웠어요.","clues":["그녀는 집주인이에요.","스팸·전단을 버리는 거예요."],"answer":"자기 집 우편함을 정리하는 거예요."},{"id":"89","situation":"뉴스 한 줄. 남자가 칼로 베였는데 상처가 없었어요.","clues":["그는 왁스 인형이었어요.","수술 연습용 모형이에요."],"answer":"연습용 모형이나 영화 촬영용이었어요."},{"id":"90","situation":"친구가 들려준 두 형제가 같은 날 같은 시각에 다른 나라에서 태어났어요.","clues":["시차가 있어요."],"answer":"한 명은 비행기 안에서 다른 시간대로 태어난 거예요."},{"id":"91","situation":"남자가 밥을 먹지 않고 1년을 살았어요.","clues":["그는 혼수상태였어요.","영양 주입이었어요."],"answer":"의학적으로 관을 통한 영양 공급만 받은 거예요."},{"id":"92","situation":"소문으로, 여자가 거울 앞에서만 옷을 갈아입어요.","clues":["그녀는 옷가게 직원이에요.","매장 규정이에요."],"answer":"피팅룸에서 일하는 직원이거나 고객이 시착하는 정상 행동이에요."},{"id":"93","situation":"어느 마을에서 남자가 물속에 들어갔는데 옷이 젖지 않았어요.","clues":["방수 옷이에요."],"answer":"다이버 슈트 등 방수 장비를 입었어요."},{"id":"94","situation":"뉴스 한 줄. 아이가 부모보다 나이가 많아 보여요.","clues":["아이는 실제 나이가 많아요.","할아버지를 부모라고 부르는 문화가 아니라 성장 호르몬·질병이에요."],"answer":"조기 성숙 질환이거나 실제로는 성인을 아이라고 부른 거예요."},{"id":"95","situation":"친구가 들려준 남자가 길에서 쓰러졌는데 지나가던 의사가 도와주지 않았어요.","clues":["의사는 가짜 의상이었어요.","의사는 연극 배우예요.","의사는 법적으로 도울 수 없는 상황이에요."],"answer":"코스프레였거나, 이미 사망 확인되어 CPR이 무의미했거나, 영화 촬영 중이었어요."},{"id":"96","situation":"여자가 매일 남의 차를 몰아도 도둑이 아니에요.","clues":["그녀는 발렛 파킹 직원이에요."],"answer":"직업상 정당하게 운전하는 거예요."},{"id":"97","situation":"소문으로, 남자가 창문을 열지 않고 방에서 사라졌어요. 10층이에요.","clues":["그는 처음부터 밖에서 들어온 게 아니에요.","인형·모형이었어요."],"answer":"창문에 비친 그림자나 인형이었어요."},{"id":"98","situation":"어느 마을에서 시계가 13시를 가리켰어요.","clues":["24시간 표기가 아니에요.","고장·개조된 시계예요.","해외 군사·특수 표기예요."],"answer":"24시간제 시계이거나 고장난 시계예요."},{"id":"99","situation":"뉴스 한 줄. 남자가 물을 마시지 않고 일주일을 버텼어요.","clues":["음식에 수분이 있었어요."],"answer":"수프·과일 등으로 수분을 섭취한 거예요."},{"id":"100","situation":"친구가 들려준 여자가 남자를 한 번도 만난 적 없는데 그의 아이를 낳았어요.","clues":["시험관·기증 정자예요.","법적으로 남편이 따로 있어요."],"answer":"인공수정 등으로 생물학적 아버지를 만나지 않은 거예요."},{"id":"101","situation":"남자가 총알을 맞았는데 구멍이 없었어요.","clues":["블랭크탄이에요.","영화 촬영이에요."],"answer":"공포탄이나 영화용 가짜 총이었어요."},{"id":"102","situation":"소문으로, 방에 빨간 벽만 있었는데 남자는 파란 벽을 봤어요.","clues":["색맹이 아니라 조명이에요."],"answer":"특수 조명이나 필터 안경으로 색이 달라 보인 거예요."},{"id":"103","situation":"어느 마을에서 남자가 매일 무료로 점심을 먹어요. 거지가 아니에요.","clues":["직장 식당이에요.","학교 급식 담당이에요."],"answer":"회사·기관에서 제공하는 직원 식사예요."},{"id":"104","situation":"뉴스 한 줄. 여자가 남편의 시체 옆에서 웃으며 전화했어요.","clues":["남편은 연기 중이었어요.","응급 상황이 연출이었어요."],"answer":"영화 촬영이나 응급처치 훈련이었어요."},{"id":"105","situation":"친구가 들려준 남자가 밤에만 글을 읽어요. 전기가 없어도 돼요.","clues":["달빛이에요."],"answer":"점자이거나 야광 인쇄, 달빛으로 읽을 수 있는 큰 글씨예요."},{"id":"106","situation":"아이가 학교 숙제를 안 했는데 선생님이 칭찬했어요.","clues":["숙제가 \"안 하는 것\"이었어요.","명상·휴식 과제예요."],"answer":"휴식·관찰 과제였던 거예요."},{"id":"107","situation":"소문으로, 남자가 돈을 버리고 행복해졌어요.","clues":["빚이 있었어요.","기부로 마음의 평화를 얻었어요."],"answer":"빚을 갚거나 기부하여 후련해진 거예요."},{"id":"108","situation":"어느 마을에서 여자가 매일 같은 옷을 입는데 더럽지 않아요.","clues":["유니폼을 여러 벌 세탁해요."],"answer":"같은 디자인의 옷을 여러 벌 갖고 있거나 온라인 캐릭터예요."},{"id":"109","situation":"뉴스 한 줄. 남자가 물속에서 불을 붙였어요.","clues":["마그네슘 등 금속 연소예요.","수중 토치예요."],"answer":"잠수용 화기나 특수 금속 연소 실험이에요."},{"id":"110","situation":"친구가 들려준 시체가 움직였어요. 좀비가 아니에요.","clues":["신경 반사예요.","물결·바람에 움직인 거예요."],"answer":"사후 근육 수축이나 물에 떠 흔들린 거예요."},{"id":"111","situation":"남자가 말을 하지 않고도 재판에서 유죄가 됐어요.","clues":["증거물이 충분했어요."],"answer":"물적 증거와 목격자로 유죄가 선고된 거예요."},{"id":"112","situation":"소문으로, 여자가 매일 남의 사진을 찍어도 불법이 아니에요.","clues":["그녀는 기자예요.","공개 행사 취재예요."],"answer":"공인의 공개 장면을 취재하는 정당한 직무예요."},{"id":"113","situation":"어느 마을에서 남자가 하루에 시계를 두 번 맞췄어요.","clues":["서머타임·시간 변경이에요.","두 개의 다른 시계예요."],"answer":"일광절약시간 전환이나 다른 시간대 시계를 맞춘 거예요."},{"id":"114","situation":"뉴스 한 줄. 방에 가구가 없는데 소리가 났어요.","clues":["이웃 집 소리예요."],"answer":"공동벽을 통해 이웃 소리가 들린 거예요."},{"id":"115","situation":"친구가 들려준 남자가 자기 이름으로 묘비가 세워졌어요. 아직 살아 있어요.","clues":["동명이인이에요.","미리 산 거예요."],"answer":"같은 이름의 다른 사람 묘비이거나 생전에 미리 산 거예요."},{"id":"116","situation":"아이가 책을 먹었어요. 위험하지 않았어요.","clues":["먹을 수 있는 종이예요.","과자 모양 책이에요.","상형 과자예요."],"answer":"식용 잉크의 케이크 장식이나 과자였어요."},{"id":"117","situation":"소문으로, 남자가 달리기에서 꼴찌였는데 금메달을 받았어요.","clues":["장애인 종목이나 나이 그룹이 달라요."],"answer":"다른 부문·종목에서 금메달이거나 릴레이 규칙상 그럴 수 있어요."},{"id":"118","situation":"어느 마을에서 여자가 매일 밤 소리를 지르는데 신고가 없어요.","clues":["그녀는 가수예요.","공연장에서 일해요."],"answer":"콘서트나 클럽에서 일하는 거예요."},{"id":"119","situation":"뉴스 한 줄. 남자가 물을 두려워하는데 서핑을 해요.","clues":["눈 위 서핑이에요.","샌드 서핑이에요."],"answer":"스노보드나 모래사장 서핑이었어요."},{"id":"120","situation":"친구가 들려준 전화부스 안 남자가 죽었고 안은 물로 가득했어요. 겨울 호수 위였어요.","clues":["부스가 얼음 위에 있었어요."],"answer":"얼음 낚시 구멍 등 위에 놓인 부스가 얼음과 함께 가라앉아 익사한 거예요."},{"id":"121","situation":"남자가 성냥을 켜고 창밖을 본 뒤 죽었어요. 잠수함 안이었어요.","clues":["실수 신호와 관련 있어요.","다른 잠수함이 있었어요."],"answer":"잠수함 간 신호를 성냥으로 잘못 보내 공격받았거나 충돌한 거예요."},{"id":"122","situation":"소문으로, 남자는 매일 지하철로 출근하는데 퇴근만 계단으로 올라가요. 같은 역이에요.","clues":["출근은 내려가는 방향이에요.","직장이 지하에 있어요.","퇴근은 위로 나와야 해요."],"answer":"지하 깊은 곳(광산·연구소 등)에서 일하고 올라올 때만 계단을 쓰는 거예요."},{"id":"123","situation":"어느 마을에서 여자는 매일 엘리베이터로 내려가기만 하고 올라탄 적이 없어요. 살고 있는 건물이에요.","clues":["그녀는 키가 작아요."],"answer":"키가 작아 혼자서는 상층 버튼을 못 누르고, 내려갈 때만 1층 버튼을 누를 수 있는 거예요."},{"id":"124","situation":"뉴스 한 줄. 남자가 총 한 발을 쐈는데 세 명이 죽었어요.","clues":["한 발에 세 명이 맞은 건 아니에요.","연쇄 사고가 났어요."],"answer":"유조차 타이어를 맞춰 폭발·연쇄 추돌로 추가 사망이 난 거예요."},{"id":"125","situation":"친구가 들려준 아이가 아빠를 보고 \"저 사람은 내 아빠가 아니에요\"라고 했는데 거짓말이 아니었어요.","clues":["아이는 거짓말하지 않았어요.","말하는 아이의 아빠는 다른 사람이에요.","가족 구성이 특이해요."],"answer":"말한 아이는 친아빠가 따로 있고, 앞에 있는 남자는 의붓아버지나 삼촌 등인 거예요."},{"id":"126","situation":"시체 옆에 물 한 웅덩이와 깃털이 있었어요. 어떻게 죽었을까요?","clues":["새가 직접 죽인 건 아니에요."],"answer":"살인자가 얼음으로 만든 날카로운 무기를 썼고, 녹아 물이 되고 깃털은 베개·이불 등에서 온 거예요."},{"id":"127","situation":"소문으로, 남자가 \"아무도 내 이름을 부르지 마\"라고 했는데 곧 죽었어요.","clues":["이름을 부른 사람이 있었어요.","그는 숨어 있었어요."],"answer":"도망 중이었는데 누군가 이름을 불러 위치가 들켜 잡히거나 공격당한 거예요."},{"id":"128","situation":"어느 마을에서 한 여자가 남편 장례식에서 웃었는데 아무도 비난하지 않았어요.","clues":["그녀는 냉정한 게 아니에요.","웃음의 이유가 따로 있어요.","남편이 연기 중이었어요."],"answer":"남편이 살아 있었거나, 장례식이 연극·촬영이었거나, 기쁜 소식을 들은 거예요."},{"id":"129","situation":"뉴스 한 줄. 남자가 물 한 방울 없이 사막을 건넜어요.","clues":["그는 걸어가지 않았어요."],"answer":"비행기나 열차 등으로 사막 위를 통과한 거예요."},{"id":"130","situation":"친구가 들려준 남자가 칼에 찔려 피 한 방울 안 나왔어요.","clues":["그는 사람이 아니에요.","인형·조각이었어요."],"answer":"인형이나 영화 소품이었어요."},{"id":"131","situation":"방 안에 시체와 물고기 한 마리가 있었어요. 물고기는 어떻게 들어왔을까요?","clues":["문은 잠겨 있었어요.","물고기는 살아 있지 않았어요.","통·병으로 들어왔어요."],"answer":"캔·병에 든 생선이나 표본이었어요."},{"id":"132","situation":"소문으로, 남자가 음악을 들으며 수영하다 익사했는데 귀는 마른 상태였어요.","clues":["수영은 실제 물이 아니에요."],"answer":"VR 수영이나 게임 속이었고 실제로 물에 들어가지 않았거나, 다른 방식의 사고였어요."},{"id":"133","situation":"어느 마을에서 여자가 거울을 보고 울었어요. 거울은 정상이었어요.","clues":["그녀는 자신의 모습을 처음 본 게 아니에요.","상황이 바뀐 뒤 거울을 봤어요."],"answer":"이별·상실 후 같은 얼굴이지만 처지가 달라져 슬퍼진 거예요."},{"id":"134","situation":"뉴스 한 줄. 남자가 책을 읽다 죽었어요. 독이 든 책은 아니었어요.","clues":["책 내용이 충격이었어요.","심장마비·과도한 스트레스와 관련 있어요.","소설 속 반전이었어요."],"answer":"충격적인 내용을 읽고 급사했거나, 책을 읽던 중 천장 등 낙하물에 맞은 거예요."},{"id":"135","situation":"친구가 들려준 두 사람이 같은 버스를 탔는데 한 명만 요금을 냈어요.","clues":["다른 한 명은 무료 대상이에요."],"answer":"한 명은 유아이거나 무료 승차 대상이거나 승무원인 거예요."},{"id":"136","situation":"남자가 밤에 길을 걷다 달을 보고 죽었어요.","clues":["달이 원인은 아니에요.","길을 보지 않고 하늘만 봤어요."],"answer":"하늘만 보고 걷다 교통사고를 당한 거예요."},{"id":"137","situation":"소문으로, 시체는 있었는데 범인의 지문은 어디에도 없었어요.","clues":["범인은 사람이 아니에요.","동물·기계·자연재해예요."],"answer":"동물 공격, 낙석, 기계 사고 등 사람 범행이 아니었어요."},{"id":"138","situation":"어느 마을에서 남자가 커피를 마시고 죽었는데 커피는 정상이었어요.","clues":["다른 행동과 겹쳤어요."],"answer":"커피 자체는 무해했지만 다른 원인(기저질환, 약, 사고)이 겹친 거예요."},{"id":"139","situation":"뉴스 한 줄. 한 여자가 매일 남의 집 편지함을 열어봐도 범죄가 아니에요.","clues":["그녀는 우편배달부예요.","직업상 권한이 있어요."],"answer":"우편집배원이 일을 하는 거예요."},{"id":"140","situation":"친구가 들려준 남자가 물속에서 숨을 쉬었어요. 마술이 아니에요.","clues":["담수가 아니에요.","액체가 물이 아닐 수 있어요.","과학 실험용 액체예요."],"answer":"산소가 녹아 있는 특수 액체나 얕은 물에서 튜브를 쓴 거예요. (또는 \"물\"이 아닌 다른 투명 액체)"},{"id":"141","situation":"아이가 부모 없이 병원에서 나왔어요. 납치가 아니에요.","clues":["아이는 막 태어났어요."],"answer":"갓 태어나 퇴원 준비 중인 정상 절차예요."},{"id":"142","situation":"소문으로, 남자가 침대에서 자다가 아침에 다른 나라에서 깼어요.","clues":["비행기 침대·기차 침대예요.","국경을 넘는 야간 이동이에요."],"answer":"국제열차나 비행기 등에서 잠든 사이 국경을 넘은 거예요."},{"id":"143","situation":"어느 마을에서 여자가 꽃을 선물받고 화를 냈어요. 꽃은 시들지 않았어요.","clues":["그녀는 알레르기가 있어요.","꽃 종류가 금기예요.","장례식장에서 장미를 받은 등 문맥이 있어요."],"answer":"장례·이별 상황에서 부적절한 꽃이었거나 알레르기였어요."},{"id":"144","situation":"뉴스 한 줄. 남자가 돈을 주고 아무것도 받지 않았는데 만족했어요.","clues":["빚을 갚았어요."],"answer":"벌금 납부나 대출 상환 등으로 \"받을 물건\"이 없는 거예요."},{"id":"145","situation":"친구가 들려준 시계는 멈췄는데 사람들은 정확한 시간을 알아요.","clues":["다른 시계가 있어요.","스마트폰이에요."],"answer":"벽시계만 고장 났고 전자기기로 시간을 보는 거예요."},{"id":"146","situation":"남자가 자신의 장례식에 참석했어요.","clues":["그는 살아 있어요.","연습·리허설이거나 사기 장례식이에요."],"answer":"연극 리허설, 영화 촬영, 또는 사기로 위장한 장례식이에요."},{"id":"147","situation":"소문으로, 여자가 이웃을 살해했다고 신고했는데 체포되지 않았어요.","clues":["이웃은 사람이 아니에요."],"answer":"벌레나 쥐 등 \"이웃\"을 은유적으로 말한 거예요."},{"id":"148","situation":"어느 마을에서 남자가 하루에 두 번 생일을 맞았어요.","clues":["날짜 변경선과 관련 있어요.","비행기로 하루를 두 번 넘겼어요."],"answer":"날짜 변경선을 넘나들며 현지에서는 같은 날 두 번 생일처럼 된 거예요."},{"id":"149","situation":"뉴스 한 줄. 문이 잠겨 있는 방에서 남자가 사라졌어요. 비밀통로는 없어요.","clues":["그는 처음부터 밖에 없었어요.","영상·사진 속 방이었어요.","녹화 화면이었어요."],"answer":"녹화된 영상 속 인물이었거나, 착시·트릭 사진이었어요."},{"id":"150","situation":"친구가 들려준 남자가 말 없이 은행에서 돈을 가져갔는데 강도가 아니에요.","clues":["그는 직원이에요."],"answer":"은행 직원이 정상 업무로 현금을 옮긴 거예요."},{"id":"151","situation":"아이가 학교에서 \"엄마가 죽였다\"고 했는데 선생님이 웃었어요.","clues":["보드게임·역할극이에요.","인형 놀이예요."],"answer":"인형 놀이나 게임에서의 이야기였어요."},{"id":"152","situation":"소문으로, 남자가 물 위를 걸었어요. 종교적 기적이 아니에요.","clues":["물이 얕아요.","다리·보트·얼음이 있어요."],"answer":"얕은 물이나 잠긴 다리, 얼어붙은 호수 위를 걸은 거예요."},{"id":"153","situation":"어느 마을에서 여자가 남편에게 이혼을 요구하지 않았는데 이혼이 성립했어요.","clues":["법원 판결·실종 선고가 있었어요."],"answer":"법적 절차로 자동 이혼·실종 처리 등이 된 거예요."},{"id":"154","situation":"뉴스 한 줄. 남자가 자기 집에서 길을 잃었어요.","clues":["집이 매우 커요.","미로 같은 구조거나 어둠이에요."],"answer":"대저택 미로, 정전, 또는 가상현경 속이었어요."},{"id":"155","situation":"친구가 들려준 시체 주머니에 돌이 들어 있었어요.","clues":["강에서 건져 올린 거예요.","시체를 가라앉히려 한 거예요."],"answer":"물에 빠진 시체를 가라앉히기 위해 주머니에 돌을 넣은 거예요."},{"id":"156","situation":"남자가 달리기 시합에서 이겼는데 상대는 더 빨랐어요.","clues":["목적지가 달랐어요."],"answer":"더 짧은 거리나 반대 방향 목표라 먼저 도착한 거예요."},{"id":"157","situation":"소문으로, 여자가 매일 밤 소리 없이 우편함을 비웠어요.","clues":["그녀는 집주인이에요.","스팸·전단을 버리는 거예요."],"answer":"자기 집 우편함을 정리하는 거예요."},{"id":"158","situation":"어느 마을에서 남자가 칼로 베였는데 상처가 없었어요.","clues":["그는 왁스 인형이었어요.","수술 연습용 모형이에요."],"answer":"연습용 모형이나 영화 촬영용이었어요."},{"id":"159","situation":"뉴스 한 줄. 두 형제가 같은 날 같은 시각에 다른 나라에서 태어났어요.","clues":["시차가 있어요."],"answer":"한 명은 비행기 안에서 다른 시간대로 태어난 거예요."},{"id":"160","situation":"친구가 들려준 남자가 밥을 먹지 않고 1년을 살았어요.","clues":["그는 혼수상태였어요.","영양 주입이었어요."],"answer":"의학적으로 관을 통한 영양 공급만 받은 거예요."},{"id":"161","situation":"여자가 거울 앞에서만 옷을 갈아입어요.","clues":["그녀는 옷가게 직원이에요.","매장 규정이에요."],"answer":"피팅룸에서 일하는 직원이거나 고객이 시착하는 정상 행동이에요."},{"id":"162","situation":"소문으로, 남자가 물속에 들어갔는데 옷이 젖지 않았어요.","clues":["방수 옷이에요."],"answer":"다이버 슈트 등 방수 장비를 입었어요."},{"id":"163","situation":"어느 마을에서 아이가 부모보다 나이가 많아 보여요.","clues":["아이는 실제 나이가 많아요.","할아버지를 부모라고 부르는 문화가 아니라 성장 호르몬·질병이에요."],"answer":"조기 성숙 질환이거나 실제로는 성인을 아이라고 부른 거예요."},{"id":"164","situation":"뉴스 한 줄. 남자가 길에서 쓰러졌는데 지나가던 의사가 도와주지 않았어요.","clues":["의사는 가짜 의상이었어요.","의사는 연극 배우예요.","의사는 법적으로 도울 수 없는 상황이에요."],"answer":"코스프레였거나, 이미 사망 확인되어 CPR이 무의미했거나, 영화 촬영 중이었어요."},{"id":"165","situation":"친구가 들려준 여자가 매일 남의 차를 몰아도 도둑이 아니에요.","clues":["그녀는 발렛 파킹 직원이에요."],"answer":"직업상 정당하게 운전하는 거예요."},{"id":"166","situation":"남자가 창문을 열지 않고 방에서 사라졌어요. 10층이에요.","clues":["그는 처음부터 밖에서 들어온 게 아니에요.","인형·모형이었어요."],"answer":"창문에 비친 그림자나 인형이었어요."},{"id":"167","situation":"소문으로, 시계가 13시를 가리켰어요.","clues":["24시간 표기가 아니에요.","고장·개조된 시계예요.","해외 군사·특수 표기예요."],"answer":"24시간제 시계이거나 고장난 시계예요."},{"id":"168","situation":"어느 마을에서 남자가 물을 마시지 않고 일주일을 버텼어요.","clues":["음식에 수분이 있었어요."],"answer":"수프·과일 등으로 수분을 섭취한 거예요."},{"id":"169","situation":"뉴스 한 줄. 여자가 남자를 한 번도 만난 적 없는데 그의 아이를 낳았어요.","clues":["시험관·기증 정자예요.","법적으로 남편이 따로 있어요."],"answer":"인공수정 등으로 생물학적 아버지를 만나지 않은 거예요."},{"id":"170","situation":"친구가 들려준 남자가 총알을 맞았는데 구멍이 없었어요.","clues":["블랭크탄이에요.","영화 촬영이에요."],"answer":"공포탄이나 영화용 가짜 총이었어요."},{"id":"171","situation":"방에 빨간 벽만 있었는데 남자는 파란 벽을 봤어요.","clues":["색맹이 아니라 조명이에요."],"answer":"특수 조명이나 필터 안경으로 색이 달라 보인 거예요."},{"id":"172","situation":"소문으로, 남자가 매일 무료로 점심을 먹어요. 거지가 아니에요.","clues":["직장 식당이에요.","학교 급식 담당이에요."],"answer":"회사·기관에서 제공하는 직원 식사예요."},{"id":"173","situation":"어느 마을에서 여자가 남편의 시체 옆에서 웃으며 전화했어요.","clues":["남편은 연기 중이었어요.","응급 상황이 연출이었어요."],"answer":"영화 촬영이나 응급처치 훈련이었어요."},{"id":"174","situation":"뉴스 한 줄. 남자가 밤에만 글을 읽어요. 전기가 없어도 돼요.","clues":["달빛이에요."],"answer":"점자이거나 야광 인쇄, 달빛으로 읽을 수 있는 큰 글씨예요."},{"id":"175","situation":"친구가 들려준 아이가 학교 숙제를 안 했는데 선생님이 칭찬했어요.","clues":["숙제가 \"안 하는 것\"이었어요.","명상·휴식 과제예요."],"answer":"휴식·관찰 과제였던 거예요."},{"id":"176","situation":"남자가 돈을 버리고 행복해졌어요.","clues":["빚이 있었어요.","기부로 마음의 평화를 얻었어요."],"answer":"빚을 갚거나 기부하여 후련해진 거예요."},{"id":"177","situation":"소문으로, 여자가 매일 같은 옷을 입는데 더럽지 않아요.","clues":["유니폼을 여러 벌 세탁해요."],"answer":"같은 디자인의 옷을 여러 벌 갖고 있거나 온라인 캐릭터예요."},{"id":"178","situation":"어느 마을에서 남자가 물속에서 불을 붙였어요.","clues":["마그네슘 등 금속 연소예요.","수중 토치예요."],"answer":"잠수용 화기나 특수 금속 연소 실험이에요."},{"id":"179","situation":"뉴스 한 줄. 시체가 움직였어요. 좀비가 아니에요.","clues":["신경 반사예요.","물결·바람에 움직인 거예요."],"answer":"사후 근육 수축이나 물에 떠 흔들린 거예요."},{"id":"180","situation":"친구가 들려준 남자가 말을 하지 않고도 재판에서 유죄가 됐어요.","clues":["증거물이 충분했어요."],"answer":"물적 증거와 목격자로 유죄가 선고된 거예요."},{"id":"181","situation":"여자가 매일 남의 사진을 찍어도 불법이 아니에요.","clues":["그녀는 기자예요.","공개 행사 취재예요."],"answer":"공인의 공개 장면을 취재하는 정당한 직무예요."},{"id":"182","situation":"소문으로, 남자가 하루에 시계를 두 번 맞췄어요.","clues":["서머타임·시간 변경이에요.","두 개의 다른 시계예요."],"answer":"일광절약시간 전환이나 다른 시간대 시계를 맞춘 거예요."},{"id":"183","situation":"어느 마을에서 방에 가구가 없는데 소리가 났어요.","clues":["이웃 집 소리예요."],"answer":"공동벽을 통해 이웃 소리가 들린 거예요."},{"id":"184","situation":"뉴스 한 줄. 남자가 자기 이름으로 묘비가 세워졌어요. 아직 살아 있어요.","clues":["동명이인이에요.","미리 산 거예요."],"answer":"같은 이름의 다른 사람 묘비이거나 생전에 미리 산 거예요."},{"id":"185","situation":"친구가 들려준 아이가 책을 먹었어요. 위험하지 않았어요.","clues":["먹을 수 있는 종이예요.","과자 모양 책이에요.","상형 과자예요."],"answer":"식용 잉크의 케이크 장식이나 과자였어요."},{"id":"186","situation":"남자가 달리기에서 꼴찌였는데 금메달을 받았어요.","clues":["장애인 종목이나 나이 그룹이 달라요."],"answer":"다른 부문·종목에서 금메달이거나 릴레이 규칙상 그럴 수 있어요."},{"id":"187","situation":"소문으로, 여자가 매일 밤 소리를 지르는데 신고가 없어요.","clues":["그녀는 가수예요.","공연장에서 일해요."],"answer":"콘서트나 클럽에서 일하는 거예요."},{"id":"188","situation":"어느 마을에서 남자가 물을 두려워하는데 서핑을 해요.","clues":["눈 위 서핑이에요.","샌드 서핑이에요."],"answer":"스노보드나 모래사장 서핑이었어요."},{"id":"189","situation":"뉴스 한 줄. 전화부스 안 남자가 죽었고 안은 물로 가득했어요. 겨울 호수 위였어요.","clues":["부스가 얼음 위에 있었어요."],"answer":"얼음 낚시 구멍 등 위에 놓인 부스가 얼음과 함께 가라앉아 익사한 거예요."},{"id":"190","situation":"친구가 들려준 남자가 성냥을 켜고 창밖을 본 뒤 죽었어요. 잠수함 안이었어요.","clues":["실수 신호와 관련 있어요.","다른 잠수함이 있었어요."],"answer":"잠수함 간 신호를 성냥으로 잘못 보내 공격받았거나 충돌한 거예요."},{"id":"191","situation":"남자는 매일 지하철로 출근하는데 퇴근만 계단으로 올라가요. 같은 역이에요.","clues":["출근은 내려가는 방향이에요.","직장이 지하에 있어요.","퇴근은 위로 나와야 해요."],"answer":"지하 깊은 곳(광산·연구소 등)에서 일하고 올라올 때만 계단을 쓰는 거예요."},{"id":"192","situation":"소문으로, 여자는 매일 엘리베이터로 내려가기만 하고 올라탄 적이 없어요. 살고 있는 건물이에요.","clues":["그녀는 키가 작아요."],"answer":"키가 작아 혼자서는 상층 버튼을 못 누르고, 내려갈 때만 1층 버튼을 누를 수 있는 거예요."},{"id":"193","situation":"어느 마을에서 남자가 총 한 발을 쐈는데 세 명이 죽었어요.","clues":["한 발에 세 명이 맞은 건 아니에요.","연쇄 사고가 났어요."],"answer":"유조차 타이어를 맞춰 폭발·연쇄 추돌로 추가 사망이 난 거예요."},{"id":"194","situation":"뉴스 한 줄. 아이가 아빠를 보고 \"저 사람은 내 아빠가 아니에요\"라고 했는데 거짓말이 아니었어요.","clues":["아이는 거짓말하지 않았어요.","말하는 아이의 아빠는 다른 사람이에요.","가족 구성이 특이해요."],"answer":"말한 아이는 친아빠가 따로 있고, 앞에 있는 남자는 의붓아버지나 삼촌 등인 거예요."},{"id":"195","situation":"친구가 들려준 시체 옆에 물 한 웅덩이와 깃털이 있었어요. 어떻게 죽었을까요?","clues":["새가 직접 죽인 건 아니에요."],"answer":"살인자가 얼음으로 만든 날카로운 무기를 썼고, 녹아 물이 되고 깃털은 베개·이불 등에서 온 거예요."},{"id":"196","situation":"남자가 \"아무도 내 이름을 부르지 마\"라고 했는데 곧 죽었어요.","clues":["이름을 부른 사람이 있었어요.","그는 숨어 있었어요."],"answer":"도망 중이었는데 누군가 이름을 불러 위치가 들켜 잡히거나 공격당한 거예요."},{"id":"197","situation":"소문으로, 한 여자가 남편 장례식에서 웃었는데 아무도 비난하지 않았어요.","clues":["그녀는 냉정한 게 아니에요.","웃음의 이유가 따로 있어요.","남편이 연기 중이었어요."],"answer":"남편이 살아 있었거나, 장례식이 연극·촬영이었거나, 기쁜 소식을 들은 거예요."},{"id":"198","situation":"어느 마을에서 남자가 물 한 방울 없이 사막을 건넜어요.","clues":["그는 걸어가지 않았어요."],"answer":"비행기나 열차 등으로 사막 위를 통과한 거예요."},{"id":"199","situation":"뉴스 한 줄. 남자가 칼에 찔려 피 한 방울 안 나왔어요.","clues":["그는 사람이 아니에요.","인형·조각이었어요."],"answer":"인형이나 영화 소품이었어요."},{"id":"200","situation":"친구가 들려준 방 안에 시체와 물고기 한 마리가 있었어요. 물고기는 어떻게 들어왔을까요?","clues":["문은 잠겨 있었어요.","물고기는 살아 있지 않았어요.","통·병으로 들어왔어요."],"answer":"캔·병에 든 생선이나 표본이었어요."}]